utils/__init__.py
utils/_utils.py
PHASER_tmp-0.0.0.dist-info/LICENSE
PHASER_tmp-0.0.0.dist-info/METADATA
PHASER_tmp-0.0.0.dist-info/WHEEL
PHASER_tmp-0.0.0.dist-info/top_level.txt
PHASER_tmp-0.0.0.dist-info/RECORD
